nott_your_timetable/__init__.py
nott_your_timetable/cli.py
nott_your_timetable/gui.py
nott_your_timetable/nott_your_timetable.py
nott_your_timetable/data/dept.json
nott_your_timetable/data/program.json
nott_your_timetable/utils/__init__.py
nott_your_timetable/utils/data.py
nott_your_timetable/utils/enums.py
nott_your_timetable/utils/parsers.py
nott_your_timetable/utils/range_handlers.py
nott_your_timetable/utils/weeks.py
nott_your_timetable-2.0.0.dist-info/LICENSE
nott_your_timetable-2.0.0.dist-info/METADATA
nott_your_timetable-2.0.0.dist-info/WHEEL
nott_your_timetable-2.0.0.dist-info/entry_points.txt
nott_your_timetable-2.0.0.dist-info/top_level.txt
nott_your_timetable-2.0.0.dist-info/RECORD
