Metadata-Version: 2.1
Name: nott-your-timetable
Version: 2.0.0
Summary: Exports Timetable for University of Nottingham Malaysia Student.
Author-email: ecyht2 <ecyht2@nottingham.edu.my>
License: GPL-3.0 license
Project-URL: Homepage, https://github.com/ecyht2/nott-your-timetable
Requires-Python: >=3.10
License-File: LICENSE
Requires-Dist: requests
Requires-Dist: icalendar
Provides-Extra: gui
Requires-Dist: PyGObject ; extra == 'gui'
